{
  "project_info": {
    "project_number": "745454232667",
    "project_id": "app-login-84e5e",
    "storage_bucket": "app-login-84e5e.firebasestorage.app"
  },
  "client": [
    {
      "client_info": {
        "mobilesdk_app_id": "1:745454232667:android:02bb2e534ed6ef4e3ecb7e",
        "android_client_info": {
          "package_name": "ipca.example.login_app"
        }
      },
      "oauth_client": [],
      "api_key": [
        {
          "current_key": "AIzaSyAdFgeLEYEZ6pPi8ZSk5zENkGMxtyZ6FxQ"
        }
      ],
      "services": {
        "appinvite_service": {
          "other_platform_oauth_client": []
        }
      }
    }
  ],
  "configuration_version": "1"
}